tappy/__init__.py
tappy/analysis.py
tappy/prediction.py
tappy/tappy.py
tappy/utils.py
tappy/tappy_lib/__init__.py
tappy/tappy_lib/filter.py
tappy/tappy_lib/parameter_database.py
tappy/tappy_lib/sparser.py
tappy/toolbox_utils/docs/conf.py
tappy/toolbox_utils/src/toolbox_utils/__init__.py
tappy/toolbox_utils/src/toolbox_utils/tsutils.py
tappy/toolbox_utils/src/toolbox_utils/readers/__init__.py
tappy/toolbox_utils/src/toolbox_utils/readers/hbn.py
tappy/toolbox_utils/src/toolbox_utils/readers/plotgen.py
tappy/toolbox_utils/src/toolbox_utils/readers/wdm.py
tappy/toolbox_utils/tests/test_asbestfreq.py
tappy/toolbox_utils/tests/test_date_slice.py
tappy/toolbox_utils/tests/test_dateparse.py
tappy/toolbox_utils/tests/test_extract.py
tappy/toolbox_utils/tests/test_hbn.py
tappy/toolbox_utils/tests/test_make_list.py
tappy/toolbox_utils/tests/test_period_timestamp.py
tappy/toolbox_utils/tests/test_plotgen.py
tappy/toolbox_utils/tests/test_range_to_numlist.py
tappy/toolbox_utils/tests/test_read.py
tappy/toolbox_utils/tests/test_wdm.py
tappy-1.2.1.dist-info/licenses/LICENSE.txt
tappy-1.2.1.dist-info/METADATA
tappy-1.2.1.dist-info/WHEEL
tappy-1.2.1.dist-info/entry_points.txt
tappy-1.2.1.dist-info/top_level.txt
tappy-1.2.1.dist-info/RECORD
