Metadata-Version: 2.4
Name: tappy
Version: 1.2.1
Summary: Command line script and Python library perform tidally-based analysis of water level data.
Author-email: Tim Cera <tim@cerazone.net>
License: BSD-3-Clause
Project-URL: bitbucket, https://bitbucket.org/timcera/tappy/src/main/
Project-URL: documentation, https://timcera.bitbucket.io/tappy/docs/index.html#tappy-documentation
Project-URL: github, https://github.com/timcera/tappy
Keywords: cli-app,python,tidal-analysis,tide-analysis,tide-filter,tide-prediction
Classifier: Development Status :: 5 - Production/Stable
Classifier: Environment :: Console
Classifier: Intended Audience :: Developers
Classifier: Intended Audience :: End Users/Desktop
Classifier: Intended Audience :: Science/Research
Classifier: License :: OSI Approved :: BSD License
Classifier: Natural Language :: English
Classifier: Operating System :: OS Independent
Classifier: Programming Language :: Python :: 3 :: Only
Classifier: Programming Language :: Python :: 3.10
Classifier: Programming Language :: Python :: 3.11
Classifier: Programming Language :: Python :: 3.12
Classifier: Programming Language :: Python :: 3.13
Classifier: Programming Language :: Python :: 3.14
Classifier: Topic :: Scientific/Engineering :: Information Analysis
Classifier: Topic :: Scientific/Engineering
Classifier: Topic :: Software Development :: Libraries :: Python Modules
Requires-Python: >=3.10
License-File: LICENSE.txt
Requires-Dist: astronomia
Requires-Dist: cltoolbox
Requires-Dist: dateparser
Requires-Dist: numpy
Requires-Dist: pandas[excel]
Requires-Dist: pint
Requires-Dist: pint-pandas
Requires-Dist: pydantic
Requires-Dist: pyparsing
Requires-Dist: pywavelets
Requires-Dist: scipy
Requires-Dist: skyfield
Requires-Dist: tabulate
Dynamic: license-file
